visualfeaturesearch/__init__.py
visualfeaturesearch/caching.py
visualfeaturesearch/data.py
visualfeaturesearch/searchtool.py
visualfeaturesearch/util.py
visualfeaturesearch/widgets.py
visualfeaturesearch-1.0.0.dist-info/METADATA
visualfeaturesearch-1.0.0.dist-info/WHEEL
visualfeaturesearch-1.0.0.dist-info/licenses/LICENSE
visualfeaturesearch-1.0.0.dist-info/RECORD
