Metadata-Version: 2.1
Name: visualfeaturesearch
Version: 1.0.0
Summary: A lightweight, interactive tool for interpreting any CNN
Project-URL: Homepage, https://github.com/lookingglasslab/VisualFeatureSearch
Author: Devon Ulrich, Ruth Fong
Maintainer-email: Devon Ulrich <dulrich000@gmail.com>
License: MIT License
License-File: LICENSE
Classifier: Framework :: Jupyter
Classifier: Operating System :: OS Independent
Classifier: Programming Language :: Python :: 3
Requires-Python: >=3.8
Requires-Dist: numpy
Requires-Dist: opencv-python
Requires-Dist: pillow
Requires-Dist: torch
Requires-Dist: torchvision
Requires-Dist: zarr
